servicefactory/Service.py
servicefactory/TestService.py
servicefactory/__init__.py
servicefactory-1.0.3.dist-info/LICENSE.txt
servicefactory-1.0.3.dist-info/METADATA
servicefactory-1.0.3.dist-info/WHEEL
servicefactory-1.0.3.dist-info/top_level.txt
servicefactory-1.0.3.dist-info/RECORD
