Metadata-Version: 2.1
Name: servicefactory
Version: 1.0.3
Summary: A highly opinionated and very convention-driven framework for creating Python "services"
Home-page: https://github.com/christophevg/py-servicefactory
Author: Christophe VG
License: MIT
Keywords: 'services framework rest api ipc
Platform: UNKNOWN
Classifier: Environment :: Console
Classifier: Development Status :: 5 - Production/Stable
Classifier: Intended Audience :: Developers
Classifier: Intended Audience :: System Administrators
Classifier: Topic :: Software Development
Classifier: License :: OSI Approved :: MIT License
Classifier: Programming Language :: Python
Classifier: Programming Language :: Python :: 2.7
Classifier: Programming Language :: Python :: 3.7
Requires-Dist: werkzeug
Requires-Dist: requests
